ansienum/__init__.py
ANSIEnum-0.2.3.dist-info/LICENSE
ANSIEnum-0.2.3.dist-info/METADATA
ANSIEnum-0.2.3.dist-info/WHEEL
ANSIEnum-0.2.3.dist-info/top_level.txt
ANSIEnum-0.2.3.dist-info/RECORD
