Metadata-Version: 2.1
Name: ANSIEnum
Version: 0.2.3
Summary: ANSIEnum: Python + ANSI = easy!
Home-page: https://gitlab.com/paulyt/ansienum
Author: Paul Taylor
Author-email: me@paulyt.co.uk
License: UNKNOWN
Platform: UNKNOWN
Classifier: Programming Language :: Python :: 3
Classifier: License :: OSI Approved :: MIT License
Classifier: Operating System :: OS Independent
Requires-Python: >=3.0
License-File: LICENSE
